dependency_parser
